kitstructlog/__init__.py
kitstructlog/main.py
kitstructlog-0.1.2.dist-info/licenses/LICENSE
kitstructlog-0.1.2.dist-info/METADATA
kitstructlog-0.1.2.dist-info/WHEEL
kitstructlog-0.1.2.dist-info/top_level.txt
kitstructlog-0.1.2.dist-info/RECORD
