Metadata-Version: 2.4
Name: kitstructlog
Version: 0.1.2
Summary: A superstructure over structlog that simplifies the configuration and use of structured logging in Python.
Author: Adam Morington
License-Expression: MIT
Project-URL: Homepage, https://github.com/morington/kitstructlog
Project-URL: Repository, https://github.com/morington/kitstructlog
Project-URL: Issues, https://github.com/morington/kitstructlog/issues
Keywords: logging,structlog,structured-logging,json-logging
Classifier: Development Status :: 4 - Beta
Classifier: Intended Audience :: Developers
Classifier: Topic :: System :: Logging
Classifier: Programming Language :: Python :: 3
Classifier: Programming Language :: Python :: 3.12
Classifier: Programming Language :: Python :: 3.13
Requires-Python: >=3.13
License-File: LICENSE
Requires-Dist: build>=1.3.0
Requires-Dist: structlog>=25.4.0
Requires-Dist: twine>=6.2.0
Dynamic: license-file
